packutil/__init__.py
packutil/path.py
packutil/version.py
packutil/versions.py
packutil/git/__init__.py
packutil/git/flow.py
packutil-0.0.4.dist-info/METADATA
packutil-0.0.4.dist-info/WHEEL
packutil-0.0.4.dist-info/top_level.txt
packutil-0.0.4.dist-info/RECORD
